adafruit_circuitpython_sgp40-1.3.22.dist-info/licenses/LICENSE
adafruit_sgp40/__init__.py
adafruit_sgp40/voc_algorithm.py
adafruit_circuitpython_sgp40-1.3.22.dist-info/METADATA
adafruit_circuitpython_sgp40-1.3.22.dist-info/WHEEL
adafruit_circuitpython_sgp40-1.3.22.dist-info/top_level.txt
adafruit_circuitpython_sgp40-1.3.22.dist-info/RECORD
