Metadata-Version: 2.4
Name: adafruit-circuitpython-sgp40
Version: 1.3.22
Summary: CircuitPython library for the Adafruit SGP40 Air Quality Sensor / VOC Index Sensor Breakouts
Author-email: Adafruit Industries <circuitpython@adafruit.com>
License: MIT
Project-URL: Homepage, https://github.com/adafruit/Adafruit_CircuitPython_SGP40
Keywords: adafruit,blinka,circuitpython,micropython,sgp40,IAQ,Air Quality,VOC,MOX,Gas
Classifier: Intended Audience :: Developers
Classifier: Topic :: Software Development :: Libraries
Classifier: Topic :: Software Development :: Embedded Systems
Classifier: Topic :: System :: Hardware
Classifier: License :: OSI Approved :: MIT License
Classifier: Programming Language :: Python :: 3
License-File: LICENSE
Requires-Dist: Adafruit-Blinka
Requires-Dist: adafruit-circuitpython-busdevice
Requires-Dist: adafruit-circuitpython-typing
Provides-Extra: optional
Dynamic: license-file
